{
    "menu_1": [
        {
            "type": "自助餐",
            "foods": "宮保雞翅、筍乾肉丁、紅燒魚丁、回鍋香腸、小瓜香腸、芹菜海絲、季節時蔬、季節時蔬."
        },
        {
            "type": "快餐",
            "foods": "培根蛋炒飯、雞塊/香腸、高麗油片絲、青菜"
        },
        {
            "type": "燴飯",
            "foods": "叉燒豬肉飯、玉米餅、花椰菜、青菜."
        },
        {
            "type": "麵食",
            "foods": "紅燒獅子 頭麵、荷包蛋、蒜味紫茄、青菜*"
        },
        {
            "type": "湯",
            "foods": "榨菜絲湯、紅茶"
        }
    ],
    "menu_2": [
        {
            "type": "自助餐",
            "foods": "白色時蔬、綠色時蔬、醬燒雞腿、黃金豬排、芝麻烤秋刀、咖哩洋芋、紅燒烤麩、洋蔥炒蛋"
        },
        {
            "type": "快餐",
            "foods": "蒜泥白肉飯 (香腸/涼拌細梗絲、滷油豆腐、炒時蔬)"
        },
        {
            "type": "燴飯",
            "foods": "茄汁蛋包飯 (雞腿堡、青菜)"
        },
        {
            "type": "麵食",
            "foods": "土魠魚羹麵 (土魠魚塊*4、滷蛋、青菜)"
        },
        {
            "type": "湯",
            "foods": "綠茶粉圓、黃芽湯"
        }
    ]
}