{
    "menu_1": [
        {
            "type": "自助餐",
            "foods": "鹹酥雞、腰果乾燒豬、豆酥魚排、肉燥豆腐、珍菇黃瓜、南瓜炒蛋、油菜、白菜滷"
        },
        {
            "type": "快餐",
            "foods": "茄汁義大利麵花枝排"
        },
        {
            "type": "燴飯",
            "foods": "泡菜肉片燴飯"
        },
        {
            "type": "麵食",
            "foods": "韓式拉麵"
        },
        {
            "type": "湯",
            "foods": "薑絲海芽湯、冬瓜山粉圓"
        }
    ],
    "menu_2": [
        {
            "type": "自助餐",
            "foods": "咕咾雞丁、滷大排、奶油炸魚、白菜豆捲、黃瓜貢丸、紅K炒蛋、綠色時蔬、白色時蔬"
        },
        {
            "type": "快餐",
            "foods": "蒲燒鯛油飯"
        },
        {
            "type": "燴飯",
            "foods": "蕃茄蛋燴飯"
        },
        {
            "type": "麵食",
            "foods": "牛肉湯餃麵"
        },
        {
            "type": "湯",
            "foods": "蔬菜湯、奶茶西米露"
        }
    ]
}