{
    "menu_1": [
        {
            "type": "自助餐",
            "foods": "咕咾肉、酥炸雞胸排、香煎魚、扁卜肉羹、三色炒蛋、辣炒筍片、薑汁海根、青菜"
        },
        {
            "type": "快餐",
            "foods": "卡啦雞套餐"
        },
        {
            "type": "燴飯",
            "foods": "蕃茄肉醬燴飯"
        },
        {
            "type": "麵食",
            "foods": "鮮菇奶油義大利麵"
        },
        {
            "type": "湯",
            "foods": "味曾黃豆芽湯、紅茶"
        }
    ],
    "menu_2": [
        {
            "type": "自助餐",
            "foods": "時令青菜2、時令青菜1、醬烤雞排、蒜泥白肉、香煎魚、梅干油腐、扁蒲燴蛋、培根高麗、茄汁洋芋"
        },
        {
            "type": "快餐",
            "foods": "油飯套餐"
        },
        {
            "type": "燴飯",
            "foods": "麻婆豆腐燴飯"
        },
        {
            "type": "麵食",
            "foods": "海鮮烏龍麵"
        },
        {
            "type": "湯",
            "foods": "綠豆湯、海芽蛋花湯"
        }
    ]
}