{
    "menu_1": [
        {
            "type": "自助餐",
            "foods": "卡拉雞排、梅干肉絲、奶油魚排、關東煮、螞蟻上樹、什錦炒蛋、豆酥高麗、綠色青菜"
        },
        {
            "type": "快餐",
            "foods": "台式炸排骨套餐"
        },
        {
            "type": "燴飯",
            "foods": "滑蛋牛肉燴飯"
        },
        {
            "type": "麵食",
            "foods": "沙茶鍋燒麵"
        },
        {
            "type": "湯",
            "foods": "白菜羹、綠茶"
        }
    ],
    "menu_2": [
        {
            "type": "自助餐",
            "foods": "碳烤雞腿排、洋蔥大排、香酥鮮魚、枸杞冬瓜雞粒、塔香海茸、蕃茄炒蛋、綠色時蔬、白色時蔬"
        },
        {
            "type": "快餐",
            "foods": "椒麻雞排飯套餐"
        },
        {
            "type": "燴飯",
            "foods": "糖醋魚片燴飯"
        },
        {
            "type": "麵食",
            "foods": "泡菜拉麵"
        },
        {
            "type": "湯",
            "foods": "清燉蘿蔔湯、麥香紅茶"
        }
    ]
}