{
    "menu_1": [
        {
            "type": "自助餐",
            "foods": "脆皮雞腿、紅燒獅子頭、香烤魚、沙茶冬粉、馬薯肉末、海芽炒蛋、綠色時蔬、白色時蔬"
        },
        {
            "type": "快餐",
            "foods": "燒烤腿排餐"
        },
        {
            "type": "燴飯",
            "foods": "什錦炒飯餐"
        },
        {
            "type": "麵食",
            "foods": "土魠魚羹麵"
        },
        {
            "type": "湯",
            "foods": "奶茶、蕃茄蔬菜湯"
        }
    ],
    "menu_2": [
        {
            "type": "自助餐",
            "foods": "香酥腿排、花枝排、沙茶肉片、蘿蔔魷魚羹、海帶干絲、柴魚蒸蛋、綠色蔬菜、白色蔬菜"
        },
        {
            "type": "快餐",
            "foods": "烤披薩套餐"
        },
        {
            "type": "燴飯",
            "foods": "日式豬排飯"
        },
        {
            "type": "麵食",
            "foods": "部隊鍋"
        },
        {
            "type": "湯",
            "foods": "海帶芽湯、冬瓜茶"
        }
    ]
}