{
    "menu_1": [
        {
            "type": "自助餐",
            "foods": "日式豬排、黃金雞排、清 蒸魚、海龍炒素肉絲、豆包、黃金餅、涼薯炒蛋、青菜"
        },
        {
            "type": "快餐",
            "foods": "蛋包飯"
        },
        {
            "type": "燴飯",
            "foods": "椒麻雞排燴飯"
        },
        {
            "type": "麵食",
            "foods": "牛肉乾拌麵"
        },
        {
            "type": "湯",
            "foods": "海帶芽湯、白木耳甜湯"
        }
    ],
    "menu_2": [
        {
            "type": "自助餐",
            "foods": "滷雞排、蘿蔔燒肉、香煎魚、蝦香扁蒲、魚香豆腐、滷白菜、海芽燴蛋、時令青菜"
        },
        {
            "type": "快餐",
            "foods": "叉燒飯"
        },
        {
            "type": "燴飯",
            "foods": "泡菜蛋燴飯"
        },
        {
            "type": "麵食",
            "foods": "泰式涼麵"
        },
        {
            "type": "湯",
            "foods": "白菜蛋花湯、冬瓜QQ圓"
        }
    ]
}