{
    "menu_1": [
        {
            "type": "自助餐",
            "foods": "沙茶大排、香酥雞胸、烤秋刀魚、酸菜豆干炸醬、香酥雞捲、長豆火腿絲、季節時蔬"
        },
        {
            "type": "快餐",
            "foods": "肉粽、炸雞翅、麵線羹、青菜"
        },
        {
            "type": "燴飯",
            "foods": "蔥爆牛肉燴飯、大溪黑乾片、荷包蛋、青菜."
        },
        {
            "type": "麵食",
            "foods": "當歸鴨肉麵、清蒸豬血糕、脆丸、青菜*"
        },
        {
            "type": "湯",
            "foods": "筍片湯、紅茶QQ"
        }
    ],
    "menu_2": [
        {
            "type": "自助餐",
            "foods": "白色蔬菜、綠色蔬菜、檸香雞柳條、筍干扣肉、豆瓣烏魚"
        },
        {
            "type": "快餐",
            "foods": "懷舊鐵路便當 (滷蛋/黃蘿蔔、滷油豆腐、炒時蔬)"
        },
        {
            "type": "燴飯",
            "foods": "三杯雞燴飯 (荷包蛋、醬燒豬血糕、炒青菜)"
        },
        {
            "type": "麵食",
            "foods": "麻醬乾拌麵 (烤大排、滷蛋、燙青菜)"
        },
        {
            "type": "湯",
            "foods": "冬瓜湯、百香蒟蒻綠茶"
        }
    ]
}