{
    "menu_1": [
        {
            "type": "自助餐",
            "foods": "蔥燒雞腿排、黑胡椒肉片、清蒸魚、紅K炒蛋、麻婆豆腐、大瓜肉羹、綠色時蔬、白色時蔬"
        },
        {
            "type": "快餐",
            "foods": "照燒豬排蓋飯"
        },
        {
            "type": "燴飯",
            "foods": "沙茶豬肉燴飯"
        },
        {
            "type": "麵食",
            "foods": "麻油雞腿麵"
        },
        {
            "type": "湯",
            "foods": "薑絲海芽湯、洛神花茶"
        }
    ],
    "menu_2": [
        {
            "type": "自助餐",
            "foods": "綠色時蔬、白色時蔬、蜜汁烤雞排、洋蔥黑胡椒豬排、香煎魚片、塔香海茸、開陽白菜、蟳絲蒸蛋"
        },
        {
            "type": "快餐",
            "foods": "奶油魚排飯"
        },
        {
            "type": "燴飯",
            "foods": "咖哩雞腿蛋包飯"
        },
        {
            "type": "麵食",
            "foods": "紅油抄手麵"
        },
        {
            "type": "湯",
            "foods": "豆花甜湯、白菜蕃茄湯"
        }
    ]
}