{
    "menu_1": [
        {
            "type": "自助餐",
            "foods": "藥膳雞腿、黑胡椒豬排、香煎魚、時令青菜2、時令青菜1、酸菜麵腸、大黃瓜炒蛋、雪片高麗、塔香茄子"
        },
        {
            "type": "快餐",
            "foods": "披薩套餐"
        },
        {
            "type": "燴飯",
            "foods": "匈牙利豬肉燴飯"
        },
        {
            "type": "麵食",
            "foods": "日式味噌拉麵"
        },
        {
            "type": "湯",
            "foods": "白菜湯、QQ甜湯"
        }
    ],
    "menu_2": [
        {
            "type": "自助餐",
            "foods": "養生雞排、香煎魚、紅燒肉排、燴雙絲、玉米豆腐、辣炒筍片、三色炒蛋、青菜"
        },
        {
            "type": "快餐",
            "foods": "卡拉雞套餐"
        },
        {
            "type": "燴飯",
            "foods": "日式豬排燴飯"
        },
        {
            "type": "麵食",
            "foods": "義大利麵"
        },
        {
            "type": "湯",
            "foods": "蛋花湯、紅茶"
        }
    ]
}