{
    "menu_1": [
        {
            "type": "自助餐",
            "foods": "香滷雞排、洋蔥肉片、香煎鮮魚、香菇胡瓜、四季豆炒肉絲、塔香黑乾、綠色時蔬、白色時蔬"
        },
        {
            "type": "快餐",
            "foods": "培根蛋炒飯餐"
        },
        {
            "type": "燴飯",
            "foods": "麻婆豆腐燴飯"
        },
        {
            "type": "麵食",
            "foods": "沙茶肉片麵"
        },
        {
            "type": "湯",
            "foods": "綠豆湯、榨菜豆皮湯"
        }
    ],
    "menu_2": [
        {
            "type": "自助餐",
            "foods": "椒鹽雞丁、海鮮排、日式豬排、青豆南瓜、沙茶海帶絲、洋蔥炒蛋、綠色蔬菜、白色蔬菜"
        },
        {
            "type": "快餐",
            "foods": "港式蘿蔔糕套餐"
        },
        {
            "type": "燴飯",
            "foods": "雞絲飯"
        },
        {
            "type": "麵食",
            "foods": "炸醬麵"
        },
        {
            "type": "湯",
            "foods": "蔬菜湯、山粉圓"
        }
    ]
}