{
    "menu_1": [
        {
            "type": "自助餐",
            "foods": "滷雞排、香酥豬排、秋刀魚、紅卜冬瓜、培根高麗、三色炒蛋、紅燒豆腐、青菜"
        },
        {
            "type": "快餐",
            "foods": "叉燒包+麵線羹"
        },
        {
            "type": "燴飯",
            "foods": "咖哩雞丁燴飯"
        },
        {
            "type": "麵食",
            "foods": "炸醬麵"
        },
        {
            "type": "湯",
            "foods": "地瓜甜湯、海芽蛋花湯"
        }
    ],
    "menu_2": [
        {
            "type": "自助餐",
            "foods": "黑椒大排、鹽酥雞、醬燒魚、髮菜蘿蔔、西芹培根、南瓜燴蛋、辣炒筍絲、時令青菜"
        },
        {
            "type": "快餐",
            "foods": "炸雞腿飯"
        },
        {
            "type": "燴飯",
            "foods": "孜然肉片燴飯"
        },
        {
            "type": "麵食",
            "foods": "藥燉雞腿麵"
        },
        {
            "type": "湯",
            "foods": "蔬菜湯、紅茶"
        }
    ]
}