{
    "menu_1": [
        {
            "type": "自助餐",
            "foods": "蔥爆雞丁、滷大排、清蒸魚、時令青菜2、時令青菜1、蕃茄高麗菜、酸菜豬血、榨菜豆干、玉米豆腐燴蛋"
        },
        {
            "type": "快餐",
            "foods": "椒麻雞飯"
        },
        {
            "type": "燴飯",
            "foods": "日式豬排飯"
        },
        {
            "type": "麵食",
            "foods": "剝皮辣椒麵"
        },
        {
            "type": "湯",
            "foods": "QQ甜湯、高麗菜湯"
        }
    ],
    "menu_2": [
        {
            "type": "自助餐",
            "foods": "宮保雞丁、梅乾控肉、香酥鱈魚排、密汁地瓜、客家小炒、辣醬甜條、花生麵筋、青菜"
        },
        {
            "type": "快餐",
            "foods": "玉米豬肉炒飯"
        },
        {
            "type": "燴飯",
            "foods": "家常肉片燴飯"
        },
        {
            "type": "麵食",
            "foods": "麻油雞腿麵"
        },
        {
            "type": "湯",
            "foods": "海芽湯、冬瓜茶"
        }
    ]
}