{
    "menu_1": [
        {
            "type": "自助餐",
            "foods": "塔香雞丁、黑胡椒豬排、樹子蒸魚、大瓜肉羹、豆干小魚、蕃茄炒蛋、綠色時蔬、白色時蔬"
        },
        {
            "type": "快餐",
            "foods": "韓式微辣焗烤飯"
        },
        {
            "type": "燴飯",
            "foods": "蠔油豬肉燴飯"
        },
        {
            "type": "麵食",
            "foods": "鴨血臭豆腐麵"
        },
        {
            "type": "湯",
            "foods": "洛神花甜湯、白玉湯"
        }
    ],
    "menu_2": [
        {
            "type": "自助餐",
            "foods": "醬燒雞排、彩椒肉片、檸檬蒸魚、蒜苗炒豆干、椒鹽甜條、玉米炒蛋、白色青菜、綠色青菜"
        },
        {
            "type": "快餐",
            "foods": "椒麻雞飯"
        },
        {
            "type": "燴飯",
            "foods": "泰式炒河粉"
        },
        {
            "type": "麵食",
            "foods": "青醬燉飯"
        },
        {
            "type": "湯",
            "foods": "薑絲冬瓜湯、紅茶"
        }
    ]
}