{
    "menu_1": [
        {
            "type": "自助餐",
            "foods": "紐奧良棒腿、蒜泥白肉、沙沙魚丁、長豆炒干丁、塔香海帶根、紅絲炒蛋、鮮菇高麗、綠色蔬菜"
        },
        {
            "type": "快餐",
            "foods": "黑胡椒肉柳潤餅"
        },
        {
            "type": "燴飯",
            "foods": "咖哩豬排燴飯"
        },
        {
            "type": "麵食",
            "foods": "抄手雙醬麵"
        },
        {
            "type": "湯",
            "foods": "綠茶QQ圓、白菜排骨湯"
        }
    ],
    "menu_2": [
        {
            "type": "自助餐",
            "foods": "椒鹽雞丁、蘑菇豬柳、檸檬魚、咖哩洋芋、蝦皮黃瓜、菜脯炒蛋、綠色時蔬、白色時蔬"
        },
        {
            "type": "快餐",
            "foods": "雞絲飯"
        },
        {
            "type": "燴飯",
            "foods": "麻婆豆腐燴飯"
        },
        {
            "type": "麵食",
            "foods": "醬燒鐵板麵"
        },
        {
            "type": "湯",
            "foods": "豬血湯、綠奶茶"
        }
    ]
}