{
    "menu_1": [
        {
            "type": "自助餐",
            "foods": "香滷雞排、香煎魚、黑胡椒豬排、小黃瓜香腸、高麗菜捲、榨菜炒肉絲、螞蟻上樹、青菜"
        },
        {
            "type": "快餐",
            "foods": "雙拼套餐"
        },
        {
            "type": "燴飯",
            "foods": "杏鮑菇豬排燴飯"
        },
        {
            "type": "麵食",
            "foods": "肉燥乾麵"
        },
        {
            "type": "湯",
            "foods": "高麗菜湯、麥片湯"
        }
    ],
    "menu_2": [
        {
            "type": "自助餐",
            "foods": "香酥魚片、糖醋肉排、蔥燒雞腿排、彩椒素雞、香辣筍干、三色豆炒蛋、木須扁蒲、時令青菜1、時令青菜2"
        },
        {
            "type": "快餐",
            "foods": "椒麻雞飯"
        },
        {
            "type": "燴飯",
            "foods": "雞肉咖哩飯"
        },
        {
            "type": "麵食",
            "foods": "肉骨茶麵"
        },
        {
            "type": "湯",
            "foods": "綠豆湯、紫菜蛋花湯"
        }
    ]
}