{
    "menu_1": [
        {
            "type": "自助餐",
            "foods": "彩椒雞柳、鐵路豬排、香酥鮮魚、枸杞冬瓜雞粒、塔香海茸、蕃茄炒蛋、綠色時蔬、白色時蔬"
        },
        {
            "type": "快餐",
            "foods": "洋蔥豬柳飯"
        },
        {
            "type": "燴飯",
            "foods": "雞絲飯"
        },
        {
            "type": "麵食",
            "foods": "酸辣湯餃麵"
        },
        {
            "type": "湯",
            "foods": "清燉蘿蔔湯、枸杞木耳"
        }
    ],
    "menu_2": [
        {
            "type": "自助餐",
            "foods": "柳葉魚、高鐵里肌、辣炒雞丁、螞蟻上樹、海帶結滷豆干、蕃茄炒蛋、枸杞冬瓜、綠色時蔬"
        },
        {
            "type": "快餐",
            "foods": "總匯披薩"
        },
        {
            "type": "燴飯",
            "foods": "三杯雞蓋飯"
        },
        {
            "type": "麵食",
            "foods": "蔥燒骨腿麵"
        },
        {
            "type": "湯",
            "foods": "玉米濃湯、花豆麥片甜湯"
        }
    ]
}